xfn/__init__.py
xfn/xfn.py
xfn-0.2.2.dist-info/LICENSE.txt
xfn-0.2.2.dist-info/METADATA
xfn-0.2.2.dist-info/WHEEL
xfn-0.2.2.dist-info/top_level.txt
xfn-0.2.2.dist-info/RECORD
