Metadata-Version: 2.1
Name: xfn
Version: 0.2.2
Summary: Clojure's transducer functionality and API in Python
Home-page: https://github.com/jjtolton/pyxfn
Author: James J. Tolton
Author-email: jjtolton@gmail.com
License: MIT
Platform: UNKNOWN
